tests/__init__.py
tests/sample_codes.py
tests/test_parser.py
tire_codes/__init__.py
tire_codes/enums.py
tire_codes/exc.py
tire_codes/main.py
tire_codes/parser.py
tire_codes/parsing_methods.py
tire_codes/regex.py
tire_codes/tire_specs.py
tire_codes/validation.py
tire_codes-0.1.0.dist-info/LICENSE
tire_codes-0.1.0.dist-info/METADATA
tire_codes-0.1.0.dist-info/WHEEL
tire_codes-0.1.0.dist-info/entry_points.txt
tire_codes-0.1.0.dist-info/top_level.txt
tire_codes-0.1.0.dist-info/RECORD
