Metadata-Version: 2.1
Name: tire_codes
Version: 0.1.0
Summary: A lightweight, dependency-free Python tool to parse and validate tire codes
Home-page: https://github.com/firstflush/tire_codes
Author: Michael Pearce
Author-email: firstflush@protonmail.com
License: MIT
Keywords: tire,codes,automotive,validation,parser,size
Classifier: Development Status :: 4 - Beta
Classifier: Intended Audience :: Developers
Classifier: Topic :: Software Development :: Libraries :: Python Modules
Classifier: License :: OSI Approved :: MIT License
Classifier: Operating System :: OS Independent
Classifier: Programming Language :: Python :: 3.10
Classifier: Programming Language :: Python :: 3.11
Requires-Python: >=3.10
License-File: LICENSE
